{"child_modules": [], "data_mtime": 1554157172, "dep_lines": [1, 1, 1], "dep_prios": [5, 30, 30], "dependencies": ["builtins", "abc", "typing"], "hash": "a9c1db982b476febe8a161912646526b", "id": "else_with_for_loop", "ignore_all": false, "interface_hash": "0f0d8ede578eb798eae8cd08e0a4c3b5", "mtime": 1554157172, "options": {"allow_redefinition": false, "allow_untyped_globals": false, "always_false": [], "always_true": [], "bazel": false, "check_untyped_defs": false, "disallow_any_decorated": false, "disallow_any_explicit": false, "disallow_any_expr": false, "disallow_any_generics": false, "disallow_any_unimported": false, "disallow_incomplete_defs": false, "disallow_subclassing_any": false, "disallow_untyped_calls": false, "disallow_untyped_decorators": false, "disallow_untyped_defs": false, "follow_imports": "silent", "follow_imports_for_stubs": false, "ignore_errors": false, "ignore_missing_imports": true, "local_partial_types": false, "mypyc": false, "new_semantic_analyzer": false, "no_implicit_optional": false, "platform": "darwin", "plugins": [], "show_none_errors": true, "strict_optional": true, "strict_optional_whitelist": null, "warn_no_return": true, "warn_return_any": false, "warn_unused_ignores": false}, "path": "/Users/skapil/Documents/work/other/py/clean_python/chapter01/else_with_for_loop.py", "size": 137, "suppressed": [], "version_id": "0.670"}