{".class": "MypyFile", "_fullname": "handle_specific_exception", "is_partial_stub_package": false, "is_stub": false, "names": {".class": "SymbolTable", "__doc__": {".class": "SymbolTableNode", "kind": "Gdef", "node": {".class": "Var", "flags": [], "fullname": "handle_specific_exception.__doc__", "name": "__doc__", "type": "builtins.str"}}, "__file__": {".class": "SymbolTableNode", "kind": "Gdef", "node": {".class": "Var", "flags": [], "fullname": "handle_specific_exception.__file__", "name": "__file__", "type": "builtins.str"}}, "__name__": {".class": "SymbolTableNode", "kind": "Gdef", "node": {".class": "Var", "flags": [], "fullname": "handle_specific_exception.__name__", "name": "__name__", "type": "builtins.str"}}, "__package__": {".class": "SymbolTableNode", "kind": "Gdef", "node": {".class": "Var", "flags": [], "fullname": "handle_specific_exception.__package__", "name": "__package__", "type": "builtins.str"}}, "get_even_list": {".class": "SymbolTableNode", "kind": "Gdef", "node": {".class": "FuncDef", "arg_kinds": [0], "arg_names": ["num_list"], "flags": [], "fullname": "handle_specific_exception.get_even_list", "name": "get_even_list", "type": null}}, "numbers": {".class": "SymbolTableNode", "kind": "Gdef", "node": {".class": "Var", "flags": [], "fullname": "handle_specific_exception.numbers", "name": "numbers", "type": {".class": "NoneTyp"}}}}, "path": "/Users/skapil/Documents/work/other/py/clean_python/chapter01/handle_specific_exception.py"}