{".class": "MypyFile", "_fullname": "small_function", "is_partial_stub_package": false, "is_stub": false, "names": {".class": "SymbolTable", "__doc__": {".class": "SymbolTableNode", "kind": "Gdef", "node": {".class": "Var", "flags": [], "fullname": "small_function.__doc__", "name": "__doc__", "type": "builtins.str"}}, "__file__": {".class": "SymbolTableNode", "kind": "Gdef", "node": {".class": "Var", "flags": [], "fullname": "small_function.__file__", "name": "__file__", "type": "builtins.str"}}, "__name__": {".class": "SymbolTableNode", "kind": "Gdef", "node": {".class": "Var", "flags": [], "fullname": "small_function.__name__", "name": "__name__", "type": "builtins.str"}}, "__package__": {".class": "SymbolTableNode", "kind": "Gdef", "node": {".class": "Var", "flags": [], "fullname": "small_function.__package__", "name": "__package__", "type": "builtins.str"}}, "get_unique_emails": {".class": "SymbolTableNode", "kind": "Gdef", "node": {".class": "FuncDef", "arg_kinds": [0], "arg_names": ["file_name"], "flags": ["is_generator"], "fullname": "small_function.get_unique_emails", "name": "get_unique_emails", "type": null}}, "print_email_list": {".class": "SymbolTableNode", "kind": "Gdef", "node": {".class": "FuncDef", "arg_kinds": [], "arg_names": [], "flags": [], "fullname": "small_function.print_email_list", "name": "print_email_list", "type": null}}, "re": {".class": "SymbolTableNode", "cross_ref": "re", "kind": "Gdef"}, "read_file": {".class": "SymbolTableNode", "kind": "Gdef", "node": {".class": "FuncDef", "arg_kinds": [0], "arg_names": ["file_name"], "flags": ["is_generator"], "fullname": "small_function.read_file", "name": "read_file", "type": null}}}, "path": "/Users/skapil/Documents/work/other/py/clean_python/chapter03/small_function.py"}